MANIFEST.in
setup.py
smvceviz/__init__.py
smvceviz/__main__.py
smvceviz.egg-info/PKG-INFO
smvceviz.egg-info/SOURCES.txt
smvceviz.egg-info/dependency_links.txt
smvceviz.egg-info/entry_points.txt
smvceviz.egg-info/top_level.txt